{
  "run_id": "ed9cf69691a34fdd95fa9c75b24fc163",
  "model_name": "logistic_saga",
  "dataset_path": "data_processed\\final\\final_dataset.parquet",
  "folds_path": "data_processed\\modeling\\city_outer_folds.csv",
  "output_dir": "C:\\Users\\golde\\OneDrive - University of Virginia\\STAT5630_FinalProject_DataProcessing\\outputs\\modeling\\logistic_saga\\full_allfolds_s10000_samplecurve-10k_2026-04-08_004723",
  "selected_feature_columns": [
    "impervious_pct",
    "elevation_m",
    "dist_to_water_m",
    "ndvi_median_may_aug",
    "land_cover_class",
    "climate_group"
  ],
  "tuning_preset": "full",
  "scoring": "average_precision",
  "selected_outer_folds": [
    0,
    1,
    2,
    3,
    4
  ],
  "sample_rows_per_city": 10000,
  "random_state": 42,
  "inner_cv_splits_requested": 4,
  "grid_search_n_jobs": 1,
  "model_n_jobs": null,
  "pipeline_cache_enabled": true,
  "pipeline_cache_root": "C:\\Users\\golde\\OneDrive - University of Virginia\\STAT5630_FinalProject_DataProcessing\\.t\\j",
  "pipeline_builder_kwargs": {
    "max_iter": 4000,
    "tol": 0.0005
  },
  "data_loading_strategy": "sampled_city_preload",
  "resume": {
    "resumed_from_existing_output_dir": false,
    "skipped_completed_outer_folds": [],
    "fold_artifacts_dir": "C:\\Users\\golde\\OneDrive - University of Virginia\\STAT5630_FinalProject_DataProcessing\\outputs\\modeling\\logistic_saga\\full_allfolds_s10000_samplecurve-10k_2026-04-08_004723\\fold_artifacts"
  },
  "search_space": {
    "param_candidate_count": 20,
    "estimated_total_inner_fits": 400,
    "requested_outer_fold_count": 5
  },
  "timing_seconds": {
    "contract_enforcement": 0.0021773000044049695,
    "fold_table_load": 0.007551400005468167,
    "sampled_city_preload": 20.13119369999913,
    "total_wall_clock": 5065.704810199997
  },
  "fold_runtime": [
    {
      "outer_fold": 0,
      "train_row_count": 240000,
      "test_row_count": 60000,
      "train_city_count": 24,
      "test_city_count": 6,
      "inner_cv_splits": 4,
      "param_candidate_count": 20,
      "estimated_inner_fit_count": 80,
      "data_load_seconds": 0.049443199997767806,
      "preprocess_build_seconds": 0.00013460000627674162,
      "preprocess_probe_fit_transform_seconds": 0.5031416999991052,
      "preprocess_output_row_count": 240000,
      "preprocess_output_feature_count": 21,
      "preprocess_output_density": 0.2857142857142857,
      "grid_search_seconds": 957.653656800001,
      "fold_wall_clock_seconds": 958.3050489000016
    },
    {
      "outer_fold": 1,
      "train_row_count": 240000,
      "test_row_count": 60000,
      "train_city_count": 24,
      "test_city_count": 6,
      "inner_cv_splits": 4,
      "param_candidate_count": 20,
      "estimated_inner_fit_count": 80,
      "data_load_seconds": 0.03891999999177642,
      "preprocess_build_seconds": 6.029999349266291e-05,
      "preprocess_probe_fit_transform_seconds": 0.5112355999881402,
      "preprocess_output_row_count": 240000,
      "preprocess_output_feature_count": 21,
      "preprocess_output_density": 0.2857142857142857,
      "grid_search_seconds": 1033.5889347000048,
      "fold_wall_clock_seconds": 1034.2327173999947
    },
    {
      "outer_fold": 2,
      "train_row_count": 240000,
      "test_row_count": 60000,
      "train_city_count": 24,
      "test_city_count": 6,
      "inner_cv_splits": 4,
      "param_candidate_count": 20,
      "estimated_inner_fit_count": 80,
      "data_load_seconds": 0.03514249999716412,
      "preprocess_build_seconds": 4.25000034738332e-05,
      "preprocess_probe_fit_transform_seconds": 0.36625720000301953,
      "preprocess_output_row_count": 240000,
      "preprocess_output_feature_count": 21,
      "preprocess_output_density": 0.2857142857142857,
      "grid_search_seconds": 1152.6066965000064,
      "fold_wall_clock_seconds": 1153.0938025000069
    },
    {
      "outer_fold": 3,
      "train_row_count": 240000,
      "test_row_count": 60000,
      "train_city_count": 24,
      "test_city_count": 6,
      "inner_cv_splits": 4,
      "param_candidate_count": 20,
      "estimated_inner_fit_count": 80,
      "data_load_seconds": 0.03432650001195725,
      "preprocess_build_seconds": 4.569999873638153e-05,
      "preprocess_probe_fit_transform_seconds": 0.46586690000549424,
      "preprocess_output_row_count": 240000,
      "preprocess_output_feature_count": 21,
      "preprocess_output_density": 0.2857142857142857,
      "grid_search_seconds": 948.5801639999991,
      "fold_wall_clock_seconds": 949.2001248999877
    },
    {
      "outer_fold": 4,
      "train_row_count": 240000,
      "test_row_count": 60000,
      "train_city_count": 24,
      "test_city_count": 6,
      "inner_cv_splits": 4,
      "param_candidate_count": 20,
      "estimated_inner_fit_count": 80,
      "data_load_seconds": 0.09959130000788718,
      "preprocess_build_seconds": 9.82999918051064e-05,
      "preprocess_probe_fit_transform_seconds": 1.0371239999949466,
      "preprocess_output_row_count": 240000,
      "preprocess_output_feature_count": 21,
      "preprocess_output_density": 0.2857142857142857,
      "grid_search_seconds": 947.523752699999,
      "fold_wall_clock_seconds": 948.903554199991
    }
  ],
  "param_grid": [
    {
      "model__C": [
        0.01,
        0.1,
        1.0,
        10.0
      ],
      "model__l1_ratio": [
        0.0
      ]
    },
    {
      "model__C": [
        0.01,
        0.1,
        1.0,
        10.0
      ],
      "model__l1_ratio": [
        1.0
      ]
    },
    {
      "model__C": [
        0.01,
        0.1,
        1.0,
        10.0
      ],
      "model__l1_ratio": [
        0.2,
        0.5,
        0.8
      ]
    }
  ],
  "output_files": {
    "predictions": "C:\\Users\\golde\\OneDrive - University of Virginia\\STAT5630_FinalProject_DataProcessing\\outputs\\modeling\\logistic_saga\\full_allfolds_s10000_samplecurve-10k_2026-04-08_004723\\heldout_predictions.parquet",
    "metrics_by_fold": "C:\\Users\\golde\\OneDrive - University of Virginia\\STAT5630_FinalProject_DataProcessing\\outputs\\modeling\\logistic_saga\\full_allfolds_s10000_samplecurve-10k_2026-04-08_004723\\metrics_by_fold.csv",
    "metrics_by_city": "C:\\Users\\golde\\OneDrive - University of Virginia\\STAT5630_FinalProject_DataProcessing\\outputs\\modeling\\logistic_saga\\full_allfolds_s10000_samplecurve-10k_2026-04-08_004723\\metrics_by_city.csv",
    "metrics_summary": "C:\\Users\\golde\\OneDrive - University of Virginia\\STAT5630_FinalProject_DataProcessing\\outputs\\modeling\\logistic_saga\\full_allfolds_s10000_samplecurve-10k_2026-04-08_004723\\metrics_summary.csv",
    "best_params_by_fold": "C:\\Users\\golde\\OneDrive - University of Virginia\\STAT5630_FinalProject_DataProcessing\\outputs\\modeling\\logistic_saga\\full_allfolds_s10000_samplecurve-10k_2026-04-08_004723\\best_params_by_fold.csv",
    "calibration_curve": "C:\\Users\\golde\\OneDrive - University of Virginia\\STAT5630_FinalProject_DataProcessing\\outputs\\modeling\\logistic_saga\\full_allfolds_s10000_samplecurve-10k_2026-04-08_004723\\calibration_curve.csv",
    "progress": "C:\\Users\\golde\\OneDrive - University of Virginia\\STAT5630_FinalProject_DataProcessing\\outputs\\modeling\\logistic_saga\\full_allfolds_s10000_samplecurve-10k_2026-04-08_004723\\progress.json",
    "progress_log": "C:\\Users\\golde\\OneDrive - University of Virginia\\STAT5630_FinalProject_DataProcessing\\outputs\\modeling\\logistic_saga\\full_allfolds_s10000_samplecurve-10k_2026-04-08_004723\\progress_log.csv",
    "fold_status": "C:\\Users\\golde\\OneDrive - University of Virginia\\STAT5630_FinalProject_DataProcessing\\outputs\\modeling\\logistic_saga\\full_allfolds_s10000_samplecurve-10k_2026-04-08_004723\\fold_status.json",
    "sampled_diagnostics": "C:\\Users\\golde\\OneDrive - University of Virginia\\STAT5630_FinalProject_DataProcessing\\outputs\\modeling\\logistic_saga\\full_allfolds_s10000_samplecurve-10k_2026-04-08_004723\\sample_diagnostics_by_city.csv"
  }
}